[{"version": "1.7.0", "autor": "mindicador.cl", "fecha": "2024-01-18T00:00:00.000Z", "uf": {"codigo": "uf", "nombre": "Unidad de fomento (UF)", "unidad_medida": "Pesos", "fecha": "2024-01-17T03:00:00.000Z", "valor": 36816.29}, "ivp": {"codigo": "ivp", "nombre": "Indice de valor promedio (IVP)", "unidad_medida": "Pesos", "fecha": "2024-01-17T03:00:00.000Z", "valor": 38121.56}, "dolar": {"codigo": "dolar", "nombre": "D\u00f3lar observado", "unidad_medida": "Pesos", "fecha": "2024-01-17T03:00:00.000Z", "valor": 922.06}, "dolar_intercambio": {"codigo": "dolar_intercambio", "nombre": "D\u00f3lar acuerdo", "unidad_medida": "Pesos", "fecha": "2014-11-13T03:00:00.000Z", "valor": 758.87}, "euro": {"codigo": "euro", "nombre": "Euro", "unidad_medida": "Pesos", "fecha": "2024-01-17T03:00:00.000Z", "valor": 1002.24}, "ipc": {"codigo": "ipc", "nombre": "Indice de Precios al Consumidor (IPC)", "unidad_medida": "Porcentaje", "fecha": "2023-12-01T03:00:00.000Z", "valor": -0.5}, "utm": {"codigo": "utm", "nombre": "Unidad Tributaria Mensual (UTM)", "unidad_medida": "Pesos", "fecha": "2024-01-01T03:00:00.000Z", "valor": 64666}, "imacec": {"codigo": "imacec", "nombre": "Imacec", "unidad_medida": "Porcentaje", "fecha": "2023-11-01T03:00:00.000Z", "valor": 1.2}, "tpm": {"codigo": "tpm", "nombre": "Tasa Pol\u00edtica Monetaria (TPM)", "unidad_medida": "Porcentaje", "fecha": "2024-01-17T03:00:00.000Z", "valor": 8.25}, "libra_cobre": {"codigo": "libra_cobre", "nombre": "Libra de Cobre", "unidad_medida": "D\u00f3lar", "fecha": "2024-01-17T03:00:00.000Z", "valor": 3.76}, "tasa_desempleo": {"codigo": "tasa_desempleo", "nombre": "Tasa de desempleo", "unidad_medida": "Porcentaje", "fecha": "2023-11-01T03:00:00.000Z", "valor": 8.73}, "bitcoin": {"codigo": "bitcoin", "nombre": "Bitcoin", "unidad_medida": "D\u00f3lar", "fecha": "2024-01-16T03:00:00.000Z", "valor": 43132.4}}, {"version": "1.7.0", "autor": "mindicador.cl", "codigo": "uf", "nombre": "Unidad de fomento (UF)", "unidad_medida": "Pesos", "serie": [{"fecha": "2024-01-17T03:00:00.000Z", "valor": 36816.29}, {"fecha": "2024-01-16T03:00:00.000Z", "valor": 36822.24}, {"fecha": "2024-01-15T03:00:00.000Z", "valor": 36828.19}, {"fecha": "2024-01-14T03:00:00.000Z", "valor": 36834.15}, {"fecha": "2024-01-13T03:00:00.000Z", "valor": 36840.1}, {"fecha": "2024-01-12T03:00:00.000Z", "valor": 36846.06}, {"fecha": "2024-01-11T03:00:00.000Z", "valor": 36852.02}, {"fecha": "2024-01-10T03:00:00.000Z", "valor": 36857.98}, {"fecha": "2024-01-09T03:00:00.000Z", "valor": 36863.94}, {"fecha": "2024-01-08T03:00:00.000Z", "valor": 36855.65}, {"fecha": "2024-01-07T03:00:00.000Z", "valor": 36847.36}, {"fecha": "2024-01-06T03:00:00.000Z", "valor": 36839.07}, {"fecha": "2024-01-05T03:00:00.000Z", "valor": 36830.78}, {"fecha": "2024-01-04T03:00:00.000Z", "valor": 36822.49}, {"fecha": "2024-01-03T03:00:00.000Z", "valor": 36814.21}, {"fecha": "2024-01-02T03:00:00.000Z", "valor": 36805.92}, {"fecha": "2024-01-01T03:00:00.000Z", "valor": 36797.64}, {"fecha": "2023-12-31T03:00:00.000Z", "valor": 36789.36}, {"fecha": "2023-12-30T03:00:00.000Z", "valor": 36781.09}, {"fecha": "2023-12-29T03:00:00.000Z", "valor": 36772.81}, {"fecha": "2023-12-28T03:00:00.000Z", "valor": 36764.54}, {"fecha": "2023-12-27T03:00:00.000Z", "valor": 36756.26}, {"fecha": "2023-12-26T03:00:00.000Z", "valor": 36747.99}, {"fecha": "2023-12-25T03:00:00.000Z", "valor": 36739.73}, {"fecha": "2023-12-24T03:00:00.000Z", "valor": 36731.46}, {"fecha": "2023-12-23T03:00:00.000Z", "valor": 36723.2}, {"fecha": "2023-12-22T03:00:00.000Z", "valor": 36714.93}, {"fecha": "2023-12-21T03:00:00.000Z", "valor": 36706.67}, {"fecha": "2023-12-20T03:00:00.000Z", "valor": 36698.41}, {"fecha": "2023-12-19T03:00:00.000Z", "valor": 36690.16}, {"fecha": "2023-12-18T03:00:00.000Z", "valor": 36681.9}]}]